pumpkin_supmcu/i2c/__init__.py
pumpkin_supmcu/i2c/master.py
pumpkin_supmcu/supmcu/__init__.py
pumpkin_supmcu/supmcu/discovery.py
pumpkin_supmcu/supmcu/i2c.py
pumpkin_supmcu/supmcu/parsing.py
pumpkin_supmcu/supmcu/serial.py
pumpkin_supmcu/supmcu/types.py
pumpkin_supmcu-1.2.3.dist-info/LICENSE.md
pumpkin_supmcu-1.2.3.dist-info/METADATA
pumpkin_supmcu-1.2.3.dist-info/WHEEL
pumpkin_supmcu-1.2.3.dist-info/top_level.txt
pumpkin_supmcu-1.2.3.dist-info/RECORD
