Metadata-Version: 2.1
Name: pumpkin-supmcu
Version: 1.2.3
Summary: A library to interface with Pumpkin SupMCU modules via I2C
Home-page: https://gitlab.com/pumpkin-space-systems/public/pumpkin-supmcu
Author: James Womack
Author-email: info@pumpkininc.com
Classifier: Programming Language :: Python :: 3
Classifier: License :: OSI Approved :: MIT License
Classifier: Operating System :: OS Independent
Requires-Python: >=3.7
License-File: LICENSE.md
Requires-Dist: pyserial
